nopi/__init__.py
nopi/nopi.py
nopi/whereyat.py
nopi-0.0.1.dist-info/LICENSE
nopi-0.0.1.dist-info/METADATA
nopi-0.0.1.dist-info/WHEEL
nopi-0.0.1.dist-info/top_level.txt
nopi-0.0.1.dist-info/RECORD
