Metadata-Version: 2.1
Name: nopi
Version: 0.0.1
Summary: New Orleans Programming Interface
Home-page: https://github.com/M-Watson/nopi
Author: Michael Watson
Author-email: 
License: UNKNOWN
Platform: UNKNOWN
Classifier: Programming Language :: Python :: 3
Classifier: License :: OSI Approved :: MIT License
Classifier: Operating System :: OS Independent
Requires-Python: >=3.6
